countries_api/__init__.py
countries_api/api_helper.py
countries_api/configuration.py
countries_api/countries_api_client.py
countries_api/decorators.py
countries_api/controllers/__init__.py
countries_api/controllers/base_controller.py
countries_api/controllers/countries_controller.py
countries_api/exceptions/__init__.py
countries_api/exceptions/api_exception.py
countries_api/http/__init__.py
countries_api/http/http_call_back.py
countries_api/http/http_client.py
countries_api/http/http_context.py
countries_api/http/http_method_enum.py
countries_api/http/http_request.py
countries_api/http/http_response.py
countries_api/http/requests_client.py
countries_api/models/__init__.py
countries_api/models/country_info.py
countries_api/models/country_response.py
tests/__init__.py
tests/http_response_catcher.py
tests/test_helper.py
tests/controllers/__init__.py
tests/controllers/controller_test_base.py
tests/controllers/test_countries_controller.py
Countries_API-1.0.dist-info/LICENSE
Countries_API-1.0.dist-info/METADATA
Countries_API-1.0.dist-info/WHEEL
Countries_API-1.0.dist-info/top_level.txt
Countries_API-1.0.dist-info/RECORD
